slack_logging_handler/__init__.py
slack_logging_handler/slack_logging_handler.py
slack_logging_handler-0.1.19.dist-info/DESCRIPTION.rst
slack_logging_handler-0.1.19.dist-info/METADATA
slack_logging_handler-0.1.19.dist-info/RECORD
slack_logging_handler-0.1.19.dist-info/WHEEL
slack_logging_handler-0.1.19.dist-info/metadata.json
slack_logging_handler-0.1.19.dist-info/top_level.txt
