Metadata-Version: 2.0
Name: slack-logging-handler
Version: 0.1.19
Summary: slack_logging_handler
Home-page: https://github.com/danie1cohen/slack_logging_handler
Author: Dan Cohen
Author-email: daniel.o.cohen@gmail.com
License: UNKNOWN
Download-URL: https://github.com/danie1cohen/slack_logging_handler/tarball/0.1.19
Platform: UNKNOWN
